{
  "generatedAt": "2026-06-11T00:00:00+03:00",
  "lastReviewed": "2026-06-11",
  "categoryMeta": {
    "emergency": {
      "label": "Acil",
      "color": "#dc2626",
      "default": true,
      "rank": 1
    },
    "official": {
      "label": "Resmi Isler",
      "color": "#0f766e",
      "default": true,
      "rank": 10
    }
  },
  "sources": [
    {
      "name": "Politecnico di Torino - Practical information",
      "url": "https://www.polito.it/en/education/international-students/practical-information",
      "note": "Accommodation, fiscal code, residence permits and health insurance basliklari."
    },
    {
      "name": "Politecnico di Torino - Maps",
      "url": "https://www.polito.it/en/maps",
      "note": "Ana kampus adresi: Corso Duca degli Abruzzi 24."
    },
    {
      "name": "EDISU Piemonte - Residenza Borsellino",
      "url": "https://www.edisu.piemonte.it/sedi/university-residence/residenza-universitaria-borsellino",
      "note": "Adres, telefon, 24 saat reception ve check-in/check-out bilgisi."
    },
    {
      "name": "EDISU Piemonte - Our canteens",
      "url": "https://www.edisu.piemonte.it/en/food-service/our-canteens",
      "note": "Campus Piemonte ID Meal ve mensa erisimi."
    },
    {
      "name": "GTT - Fares",
      "url": "https://www.gtt.to.it/cms/en/fares",
      "note": "Under 26 aylik pass ve guncel tarife kontrolu."
    },
    {
      "name": "GTT - Service information",
      "url": "https://www.gtt.to.it/cms/en/information",
      "note": "Journey planner, live arrivals, timetables and Telegram bot."
    },
    {
      "name": "GTT - Journey planner",
      "url": "https://www.gtt.to.it/cms/en/ricerca-percorsi",
      "note": "PLAN A JOURNEY, stop search, lines and routes."
    },
    {
      "name": "GTT - Points of sale",
      "url": "https://www.gtt.to.it/cms/en/pointsale",
      "note": "Authorized outlets, ToMove app, Tap & Go and ticket vending machines."
    },
    {
      "name": "MATO / Muoversi a Torino",
      "url": "https://www.muoversiatorino.it/",
      "note": "Torino infomobility portal and route fallback."
    },
    {
      "name": "Moovit Torino",
      "url": "https://moovitapp.com/index/en/public_transit-Torino-222",
      "note": "Alternative route and live transit planning."
    },
    {
      "name": "EDISU Piemonte - The food service",
      "url": "https://www.edisu.piemonte.it/en/food-service/food-service",
      "note": "Incoming international mobility students can use the service at the request of the host university."
    },
    {
      "name": "Universita di Torino - Emergency numbers",
      "url": "https://en.unito.it/living-turin/when-you-arrive/emergency-and-public-service-numbers",
      "note": "Torino icin 112, 113, 115, 118 ve diger acil numaralar."
    },
    {
      "name": "Farmacie Comunali Torino - Farmacie aperte ora",
      "url": "https://www.farmaciecomunalitorino.it/farmacie-aperte-ora/",
      "note": "Acik eczane kontrolu."
    }
  ],
  "pois": [
    {
      "id": "guide-emergency-mauriziano",
      "name": "Pronto Soccorso - Ospedale Mauriziano",
      "lat": 45.04978,
      "lng": 7.66539,
      "category": "emergency",
      "priority": 111,
      "description": "Politecnico/Borsellino tarafina gore yakin buyuk acil servis adaylarindan biri. Gercek acilde once 112 ara.",
      "address": "Largo Filippo Turati 62, Torino",
      "cost": "Acil durumda 112; rutin islemde randevu ve resmi yonlendirme gerekebilir.",
      "tags": ["acil", "hastane", "pronto soccorso", "112"],
      "link": "https://www.mauriziano.it/",
      "markerLabel": "SOS",
      "source": "Erasmus Guide"
    },
    {
      "id": "guide-emergency-molinette",
      "name": "Pronto Soccorso - Ospedale Molinette",
      "lat": 45.04042,
      "lng": 7.67432,
      "category": "emergency",
      "priority": 108,
      "description": "Torino'nun ana hastane bolgesindeki acil servis referansi. Gercek acilde once 112 ara.",
      "address": "Corso Bramante 88, Torino",
      "cost": "Acil durumda 112; ulasim icin Google Maps/ambulans yonlendirmesini kullan.",
      "tags": ["acil", "hastane", "pronto soccorso", "112"],
      "link": "https://www.cittadellasalute.to.it/",
      "markerLabel": "SOS",
      "source": "Erasmus Guide"
    },
    {
      "id": "guide-emergency-night-pharmacy-xx-settembre",
      "name": "Farmacia Comunale 42 - gece nobeti",
      "lat": 45.0732,
      "lng": 7.68447,
      "category": "emergency",
      "priority": 101,
      "description": "Farmacie Comunali Torino sayfasinda gece hizmeti icin listelenen merkez eczane. Gitmeden once acik eczane sayfasindan kontrol et.",
      "address": "Via XX Settembre 5, Torino",
      "cost": "Gece/nobet bilgisi degisebilir; farmacie aperte ora linkinden teyit et.",
      "tags": ["eczane", "farmacia", "gece", "nobet"],
      "link": "https://www.farmaciecomunalitorino.it/farmacie-aperte-ora/",
      "markerLabel": "PH",
      "source": "Erasmus Guide"
    },
    {
      "id": "guide-official-immigration-desk",
      "name": "PoliTO Immigration Desk",
      "lat": 45.062895,
      "lng": 7.658964,
      "category": "official",
      "priority": 112,
      "description": "Visa, permesso di soggiorno ve health insurance surecleri icin PoliTO destek noktasi.",
      "address": "Main Campus Cittadella Politecnica, Corso Castelfidardo 39, Torino",
      "cost": "E-posta: immigration.desk@polito.it. Gitmeden once acilis saati ve randevuyu kontrol et.",
      "tags": ["immigration desk", "permesso", "visa", "health insurance", "PoliTO"],
      "link": "https://www.polito.it/en/education/international-students/practical-information/residence-permits-and-stay-requirements",
      "markerLabel": "VISA",
      "source": "Erasmus Guide"
    },
    {
      "id": "guide-official-edisu-torino",
      "name": "EDISU Torino - ogrenci hizmetleri",
      "lat": 45.04583,
      "lng": 7.68014,
      "category": "official",
      "priority": 103,
      "description": "Burs, yurt, mensa ve ogrenci destek islemleri icin EDISU referansi.",
      "address": "Via Madama Cristina 83, Torino",
      "cost": "Basvuru ve randevu durumunu EDISU resmi sayfasindan kontrol et.",
      "tags": ["EDISU", "mensa", "residence", "student support"],
      "link": "https://www.edisu.piemonte.it/en",
      "markerLabel": "EDISU",
      "source": "Erasmus Guide"
    },
    {
      "id": "guide-food-castelfidardo",
      "name": "EDISU Castelfidardo Politecnico Mensa",
      "lat": 45.06502,
      "lng": 7.65948,
      "category": "food",
      "priority": 112,
      "description": "Politecnico ve Borsellino icin en kritik EDISU mensa. Campus Piemonte ID Meal ile erisim/odeme gerekir.",
      "address": "Corso Castelfidardo 30/A, Torino",
      "cost": "Tarife, host university talebi ve ID Meal durumuna gore degisir; gitmeden EDISU sayfasini kontrol et.",
      "tags": ["mensa", "EDISU", "Politecnico", "Campus Piemonte ID Meal", "gluten free"],
      "link": "https://www.edisu.piemonte.it/en/locations/mensa-universitaria/castelfidardo-politecnico-canteen",
      "markerLabel": "MENS",
      "source": "Erasmus Guide"
    },
    {
      "id": "guide-food-borsellino",
      "name": "EDISU Borsellino Mensa",
      "lat": 45.0662,
      "lng": 7.65635,
      "category": "food",
      "priority": 111,
      "description": "Borsellino yurdu cevresindeki ana EDISU mensa. Campus Piemonte ID Meal ile erisim/odeme gerekir.",
      "address": "Via Andrea Vochieri 6/A, Torino",
      "cost": "Acil not: kapanis ve saatler degisebilir; EDISU duyurularini kontrol et.",
      "tags": ["mensa", "EDISU", "Borsellino", "Campus Piemonte ID Meal", "gluten free"],
      "link": "https://www.edisu.piemonte.it/en/locations/mensa-universitaria/borsellino-university-canteen",
      "markerLabel": "MENS",
      "source": "Erasmus Guide"
    },
    {
      "id": "guide-food-olimpia",
      "name": "EDISU Olimpia Mensa",
      "lat": 45.07378,
      "lng": 7.69935,
      "category": "food",
      "priority": 104,
      "description": "Campus Einaudi/Lungo Dora Siena tarafinda EDISU mensa alternatifi. Campus Piemonte ID Meal gerekir.",
      "address": "Lungo Dora Siena 102/B, Torino",
      "cost": "Saat ve kapanislari EDISU sayfasindan kontrol et.",
      "tags": ["mensa", "EDISU", "Olimpia", "Campus Piemonte ID Meal", "gluten free"],
      "link": "https://www.edisu.piemonte.it/en/locations/mensa-universitaria/olimpia-university-canteen",
      "markerLabel": "MENS",
      "source": "Erasmus Guide"
    },
    {
      "id": "guide-food-principe-amedeo",
      "name": "EDISU Principe Amedeo Mensa",
      "lat": 45.06602,
      "lng": 7.69205,
      "category": "food",
      "priority": 103,
      "description": "Merkez/Palazzo Nuovo tarafinda EDISU mensa alternatifi. Campus Piemonte ID Meal gerekir.",
      "address": "Via Principe Amedeo 48, Torino",
      "cost": "Saat ve kapanislari EDISU sayfasindan kontrol et.",
      "tags": ["mensa", "EDISU", "Principe Amedeo", "Campus Piemonte ID Meal", "gluten free"],
      "link": "https://www.edisu.piemonte.it/en/locations/mensa-universitaria/principe-amedeo-university-canteen",
      "markerLabel": "MENS",
      "source": "Erasmus Guide"
    },
    {
      "id": "guide-food-river",
      "name": "EDISU Ristoreria River",
      "lat": 45.05999,
      "lng": 7.69266,
      "category": "food",
      "priority": 101,
      "description": "Murazzi/Po nehri tarafinda EDISU mensa alternatifi. Campus Piemonte ID Meal gerekir.",
      "address": "Murazzi del Po 22, Torino",
      "cost": "Saat, hizmet arasi ve kapanislari EDISU duyurularindan kontrol et.",
      "tags": ["mensa", "EDISU", "Ristoreria River", "Campus Piemonte ID Meal", "gluten free"],
      "link": "https://www.edisu.piemonte.it/en/locations/mensa-universitaria/river-canteen",
      "markerLabel": "MENS",
      "source": "Erasmus Guide"
    }
  ],
  "savedAddresses": [
    {
      "label": "Yurdum",
      "value": "Residenza Universitaria Borsellino, Via Paolo Borsellino 42, 10138 Torino",
      "phone": "+39 011 4308758 / +39 011 4474001"
    },
    {
      "label": "PoliTO",
      "value": "Politecnico di Torino, Corso Duca degli Abruzzi 24, 10129 Torino"
    },
    {
      "label": "Immigration Desk",
      "value": "Cittadella Politecnica, Corso Castelfidardo 39, Torino",
      "phone": "immigration.desk@polito.it"
    }
  ],
  "emergencyNumbers": [
    {
      "label": "112",
      "detail": "Tum aciller"
    },
    {
      "label": "113",
      "detail": "Polis"
    },
    {
      "label": "115",
      "detail": "Itfaiye"
    },
    {
      "label": "118",
      "detail": "Ambulans"
    }
  ],
  "phrases": [
    {
      "it": "Mi sono perso.",
      "tr": "Kayboldum."
    },
    {
      "it": "Devo andare a questo indirizzo.",
      "tr": "Bu adrese gitmem gerekiyor."
    },
    {
      "it": "Puo aiutarmi?",
      "tr": "Yardimci olabilir misiniz?"
    },
    {
      "it": "Non parlo bene italiano.",
      "tr": "Italyancam iyi degil."
    },
    {
      "it": "Sono uno studente Erasmus traineeship.",
      "tr": "Erasmus staj ogrencisiyim."
    }
  ],
  "dailyModes": [
    {
      "id": "first-day",
      "label": "Ilk gun",
      "categories": ["personal", "official", "transport", "cheap", "shopping", "gtt", "food"],
      "query": ""
    },
    {
      "id": "school-day",
      "label": "Okul",
      "categories": ["personal", "student", "food", "cheap", "transport"],
      "query": ""
    },
    {
      "id": "paperwork",
      "label": "Resmi is",
      "categories": ["official", "practical", "personal", "gtt", "atm"],
      "query": ""
    },
    {
      "id": "night",
      "label": "Gece",
      "categories": ["personal", "transport", "emergency", "halal", "gtt"],
      "query": ""
    }
  ],
  "searchPresets": [
    {
      "label": "Market",
      "query": "Lidl Aldi Eurospin supermarket"
    },
    {
      "label": "Eczane",
      "query": "pharmacy farmacia"
    },
    {
      "label": "Yemek",
      "query": "mensa EDISU halal cheap pizza kebab"
    },
    {
      "label": "SIM",
      "query": "TIM Vodafone Iliad WindTre electronics"
    }
  ],
  "quickRoutes": [
    {
      "label": "Havaalani -> Yurt",
      "href": "https://www.google.com/maps/dir/?api=1&origin=45.191576,7.641578&destination=45.066123,7.657138&travelmode=transit"
    },
    {
      "label": "Yurt -> PoliTO",
      "href": "https://www.google.com/maps/dir/?api=1&origin=45.066123,7.657138&destination=45.06302,7.66214&travelmode=walking"
    },
    {
      "label": "PoliTO -> Yurt",
      "href": "https://www.google.com/maps/dir/?api=1&origin=45.06302,7.66214&destination=45.066123,7.657138&travelmode=walking"
    },
    {
      "label": "PoliTO -> Porta Susa",
      "href": "https://www.google.com/maps/dir/?api=1&origin=45.06302,7.66214&destination=45.071576,7.665855&travelmode=transit"
    },
    {
      "label": "PoliTO -> Porta Nuova",
      "href": "https://www.google.com/maps/dir/?api=1&origin=45.06302,7.66214&destination=45.06276,7.679&travelmode=transit"
    },
    {
      "label": "Yurt -> Market",
      "href": "https://www.google.com/maps/search/?api=1&query=supermarket%20near%20Via%20Paolo%20Borsellino%2042%20Torino"
    },
    {
      "label": "Yurt -> Eczane",
      "href": "https://www.google.com/maps/search/?api=1&query=pharmacy%20near%20Via%20Paolo%20Borsellino%2042%20Torino"
    },
    {
      "label": "Gece eczanesi",
      "href": "https://www.farmaciecomunalitorino.it/farmacie-aperte-ora/"
    }
  ],
  "transitTools": [
    {
      "label": "Resmi rota planlayıcı",
      "description": "GTT resmi rota planlama, durak arama, hatlar ve güzergahlar.",
      "href": "https://www.gtt.to.it/cms/en/ricerca-percorsi"
    },
    {
      "label": "Canlı varışlar",
      "description": "GTT bilgi sayfasi: canli otobus/tramvay varisi, saatler ve rota haritalari.",
      "href": "https://www.gtt.to.it/cms/en/information"
    },
    {
      "label": "gttorari_bot",
      "description": "Telegram bot: durak varis bilgisi ve yakindaki yetkili satis noktasi.",
      "href": "https://telegram.me/gttorari_bot"
    },
    {
      "label": "Google toplu taşıma",
      "description": "Canli rota icin hizli Maps fallback.",
      "href": "https://www.google.com/maps/dir/?api=1&destination=Torino&travelmode=transit"
    },
    {
      "label": "Moovit",
      "description": "Alternatif rota ve hat takibi.",
      "href": "https://moovitapp.com/index/en/public_transit-Torino-222"
    },
    {
      "label": "MATO",
      "description": "Muoversi a Torino infomobility portali.",
      "href": "https://www.muoversiatorino.it/"
    },
    {
      "label": "Satış noktaları",
      "description": "Bilet ve abonman satis noktalarini kontrol et.",
      "href": "https://www.gtt.to.it/cms/en/pointsale"
    },
    {
      "label": "Offline yedek",
      "description": "Canli bilgi yoksa Maps toplu tasima rotasini ac.",
      "href": "https://www.google.com/maps/search/?api=1&query=GTT%20ticket%20Torino"
    }
  ],
  "transitPasses": [
    {
      "title": "Şehir içi + çevre abonman",
      "detail": "Sehir ici + cevre GTT agi icin bilet/abonman basliklarini resmi fares sayfasindan kontrol et.",
      "href": "https://www.gtt.to.it/cms/en/fares"
    },
    {
      "title": "26 yaş altı abonman",
      "detail": "Under 26 aylik/yillik pass ve BIP kart kosullari degisebilir; satin almadan resmi sayfayi kontrol et.",
      "href": "https://www.gtt.to.it/cms/en/fares"
    },
    {
      "title": "Tren + toplu taşıma",
      "detail": "Tren + Torino toplu tasima kombinasyonlari icin GTT fares sayfasindaki basligi kullan.",
      "href": "https://www.gtt.to.it/cms/en/fares"
    }
  ],
  "foodGuide": {
    "alerts": [
      "⚠️ Agustos Mensa Uyarisi: EDISU yemekhaneleri genelde yil boyunca 11 ay acik olur; bazi yemekhaneler Agustos'ta kapanabilir. Alternatif: market + ucuz restoran listesine bak.",
      "Incoming Erasmus ogrencileri icin yemek hizmeti host university talebiyle acilabilir; EDISU/PoliTO surecini kontrol et.",
      "Tum mensalarda erisim ve odeme icin Campus Piemonte ID Meal uygulamasi gerekir."
    ],
    "links": [
      {
        "label": "EDISU yemek hizmeti",
        "href": "https://www.edisu.piemonte.it/en/food-service/food-service"
      },
      {
        "label": "Yemekhaneler",
        "href": "https://www.edisu.piemonte.it/en/food-service/our-canteens"
      },
      {
        "label": "Campus Piemonte ID Meal",
        "href": "https://www.edisu.piemonte.it/en/food-service/our-canteens"
      }
    ],
    "canteens": [
      "Castelfidardo Politecnico",
      "Borsellino",
      "Olimpia",
      "Principe Amedeo",
      "Ristoreria River"
    ],
    "searches": [
      {
        "label": "Ucuz market",
        "query": "Lidl Aldi Eurospin IN's Mercato supermarket"
      },
      {
        "label": "Helal/Turk market",
        "query": "halal Turkish market ethnic supermarket"
      },
      {
        "label": "Kebab/pizza",
        "query": "halal kebab pizza cheap"
      },
      {
        "label": "Gece yemek",
        "query": "late night food kebab pizza Torino"
      },
      {
        "label": "Calisma kafe",
        "query": "cafe study wifi Politecnico Torino"
      }
    ]
  },
  "officialGroups": [
    {
      "title": "PoliTO",
      "links": [
        {
          "label": "Pratik bilgiler",
          "href": "https://www.polito.it/en/education/international-students/practical-information"
        },
        {
          "label": "Kampus haritaları",
          "href": "https://www.polito.it/en/maps"
        },
        {
          "label": "Codice fiscale",
          "href": "https://www.polito.it/en/education/international-students/practical-information/fiscal-code"
        },
        {
          "label": "Sağlık sigortası",
          "href": "https://www.polito.it/en/education/international-students/practical-information/health-insurance"
        },
        {
          "label": "Oturum izni",
          "href": "https://www.polito.it/en/education/international-students/practical-information/residence-permits-and-stay-requirements"
        }
      ]
    },
    {
      "title": "EDISU",
      "links": [
        {
          "label": "Borsellino yurdu",
          "href": "https://www.edisu.piemonte.it/sedi/university-residence/residenza-universitaria-borsellino"
        },
        {
          "label": "Yemekhaneler",
          "href": "https://www.edisu.piemonte.it/en/food-service/our-canteens"
        },
        {
          "label": "EDISU noktaları",
          "href": "https://www.edisu.piemonte.it/sedi"
        }
      ]
    },
    {
      "title": "GTT",
      "links": [
        {
          "label": "Ücretler",
          "href": "https://www.gtt.to.it/cms/en/fares"
        },
        {
          "label": "Canlı bilgi",
          "href": "https://www.gtt.to.it/cms/en/information"
        },
        {
          "label": "TO Move",
          "href": "https://www.gtt.to.it/cms/app"
        },
        {
          "label": "Telegram bot",
          "href": "https://telegram.me/gttorari_bot"
        }
      ]
    },
    {
      "title": "Yasam",
      "links": [
        {
          "label": "Acil numaralar",
          "href": "https://en.unito.it/living-turin/when-you-arrive/emergency-and-public-service-numbers"
        },
        {
          "label": "Acik eczane",
          "href": "https://www.farmaciecomunalitorino.it/farmacie-aperte-ora/"
        },
        {
          "label": "ESN Torino",
          "href": "https://torino.esn.it/"
        }
      ]
    }
  ],
  "checklists": [
    {
      "title": "Ilk hafta",
      "items": [
        {
          "id": "passport",
          "label": "Pasaport / kimlik"
        },
        {
          "id": "visa",
          "label": "Vize / stay proseduru"
        },
        {
          "id": "insurance",
          "label": "Health insurance"
        },
        {
          "id": "fiscal-code",
          "label": "Codice fiscale"
        },
        {
          "id": "housing",
          "label": "EDISU / konaklama"
        },
        {
          "id": "gtt",
          "label": "GTT kart / TO Move"
        },
        {
          "id": "sim",
          "label": "SIM kart"
        },
        {
          "id": "polito-portal",
          "label": "PoliTO portal"
        },
        {
          "id": "lab-contact",
          "label": "Lab / hoca iletisim"
        },
        {
          "id": "emergency",
          "label": "Acil numaralar"
        }
      ]
    }
  ],
  "alerts": [
    "EDISU mensa ve residence kapanislari ozellikle Agustos doneminde degisebilir; resmi sayfadan kontrol et.",
    "GTT fiyat, grev ve hat bilgileri degisebilir; canli bilgi ve resmi tarife linklerini oncelikli kullan.",
    "Ozel belge, kart veya pasaport numaralarini public GitHub Pages dosyalarina yazma."
  ],
  "privacyWarnings": [
    "Pasaport numarasi, kart bilgisi, kapi kodu, oda numarasi, ozel telefonlar ve belge linklerini public GitHub Pages koduna yazma.",
    "Notlar sadece bu cihazdaki localStorage icinde saklanir; ortak cihazda Private Mode'u kapat veya notlari temizle.",
    "Kimlik, sigorta belgesi veya belge PDF linkleri icin bu siteyi depo gibi kullanma."
  ]
}
